<?xml version="1.0" encoding="UTF-8"?>
<list xmlns:xsi="http://www.w3.org/2001/XMLSchema-instance" xsi:noNamespaceSchemaLocation="../../../xsd/DropListData.xsd">
<!-- Людоед Турак -->
<npc id="20248">
	<droplist>
		<category id="1" chance="70">
			<item id="57" min="239" max="476" chance="100"/> <!-- Адена -->
		</category>
		<category id="2" chance="0.0962">
			<item id="86" min="1" max="1" chance="1.2938"/> <!-- Томагавк -->
			<item id="179" min="1" max="1" chance="1.2938"/> <!-- Булава Послушника -->
			<item id="180" min="1" max="1" chance="1.2938"/> <!-- Булава Правосудия -->
			<item id="2022" min="1" max="1" chance="49.929"/> <!-- Навершие Булавы Правосудия -->
			<item id="181" min="1" max="1" chance="1.2938"/> <!-- Булава Мага -->
			<item id="182" min="1" max="1" chance="1.2938"/> <!-- Молот Рока -->
			<item id="183" min="1" max="1" chance="1.2938"/> <!-- Посох Мистика -->
			<item id="184" min="1" max="1" chance="1.2938"/> <!-- Посох Заклинателя -->
			<item id="2023" min="1" max="1" chance="39.7205"/> <!-- Навершие Посоха Заклинателя -->
			<item id="185" min="1" max="1" chance="1.2939"/> <!-- Посох Маны -->
		</category>
		<category id="3" chance="13.3641">
			<item id="34991" min="4" max="4" chance="41.0042" /> <!-- Обломок Доспеха -->
			<item id="34992" min="1" max="1" chance="38.4414" /> <!-- Драгоценные Аксессуары -->
			<item id="1874" min="1" max="1" chance="2.5628"/> <!-- Орихаруконовая Руда -->
			<item id="1829" min="1" max="1" chance="15.3766"/> <!-- Свиток Телепорта: Холл Клана -->
			<item id="2274" min="1" max="1" chance="0.2746"/> <!-- Рецепт - Череполом -->
			<item id="2192" min="1" max="1" chance="4.9032"/> <!-- Рецепт - Треугольный Щит -->
		</category>
	</droplist>
	<spoillist>
		<item id="2250" min="1" max="1" chance="14.1016"/> <!-- Рецепт - Костяная Стрела -->
		<item id="955" min="1" max="1" chance="0.2256"/> <!-- Свиток: Модифицировать Оружие (D) -->
		<item id="34992" min="1" max="1" chance="56.4065" /> <!-- Драгоценные Аксессуары -->
	</spoillist>
</npc>
</list>
