<?xml version="1.0" encoding="UTF-8"?>
<list xmlns:xsi="http://www.w3.org/2001/XMLSchema-instance" xsi:noNamespaceSchemaLocation="../../../xsd/DropListData.xsd">
<!-- Воин Орков Барак -->
<npc id="20372">
	<droplist>
		<category id="1" chance="70">
			<item id="57" min="81" max="110" chance="100"/> <!-- Адена -->
		</category>
		<category id="2" chance="0.4132">
			<item id="3" min="1" max="1" chance="22.5806"/> <!-- Широкий Меч -->
			<item id="2005" min="1" max="1" chance="77.4194"/> <!-- Клинок Широкого Меча -->
		</category>
		<category id="3" chance="10.5294">
			<item id="34990" min="1" max="1" chance="28.3582" /> <!-- Обломок Оружия -->
			<item id="34992" min="1" max="1" chance="56.7164" /> <!-- Драгоценные Аксессуары -->
			<item id="1814" min="1" max="1" chance="14.9254"/> <!-- Рецепт - Кожа -->
		</category>
	</droplist>
	<spoillist>
		<item id="34991" min="1" max="1" chance="30.3262" /> <!-- Обломок Доспеха -->
		<item id="1870" min="1" max="1" chance="15.1631"/> <!-- Уголь -->
		<item id="34992" min="1" max="1" chance="30.3261" /> <!-- Драгоценные Аксессуары -->
	</spoillist>
</npc>
</list>
