<?xml version="1.0" encoding="UTF-8"?>
<list xmlns:xsi="http://www.w3.org/2001/XMLSchema-instance" xsi:noNamespaceSchemaLocation="../../../xsd/DropListData.xsd">
<!-- Воитель Язычник -->
<npc id="21441">
	<droplist>
		<category id="1" chance="70.000">
			<item id="57" min="269" max="546" chance="100.00000" />		<!-- Адена -->
		</category>
		<category id="2" chance="0.040">
			<item id="11946" min="1" max="1" chance="1.71506" />		<!-- Обычный Предмет - Посох Даспариона -->
			<item id="5543" min="1" max="1" chance="21.20695" />		<!-- Навершие Посоха Даспариона -->
			<item id="11949" min="1" max="1" chance="1.71506" />		<!-- Обычный Предмет - Метеоритный Дождь -->
			<item id="5532" min="1" max="1" chance="21.00888" />		<!-- Навершие Метеоритного Дождя -->
			<item id="11953" min="1" max="1" chance="1.71506" />		<!-- Обычный Предмет - Глаз Духа -->
			<item id="8341" min="1" max="1" chance="20.98202" />		<!-- Осколок Глаза Духа -->
			<item id="11958" min="1" max="1" chance="1.71506" />		<!-- Обычный Предмет - Молот Разрушителя -->
			<item id="8346" min="1" max="1" chance="21.00888" />		<!-- Часть Молота Разрушителя -->
			<item id="212" min="1" max="1" chance="2.23325" />		<!-- Посох Даспариона -->
			<item id="2504" min="1" max="1" chance="2.23325" />		<!-- Метеоритный Дождь -->
			<item id="7894" min="1" max="1" chance="2.23325" />		<!-- Глаз Духа -->
			<item id="7899" min="1" max="1" chance="2.23325" />		<!-- Молот Разрушителя -->
		</category>
		<category id="3" chance="6.523">
			<item id="34991" min="4" max="4" chance="29.8243" /> <!-- Обломок Доспеха -->
			<item id="34992" min="1" max="1" chance="27.96030" /> <!-- Драгоценные Аксессуары -->
			<item id="1874" min="1" max="1" chance="1.86400" />		<!-- Орихаруконовая Руда -->
			<item id="4043" min="1" max="1" chance="0.93200" />		<!-- Азоф -->
			<item id="34990" min="2" max="2" chance="0.93200" /> <!-- Обломок Оружия -->
			<item id="5442" min="1" max="1" chance="0.01040" />		<!-- Рецепт - Пронзатель Душ (60%) -->
			<item id="8730" min="1" max="1" chance="0.31070" />		<!-- Камень Жизни - Уровень 67 -->
			<item id="8740" min="1" max="1" chance="0.07770" />		<!-- Камень Жизни Среднего Качества - Уровень 67 -->
			<item id="8750" min="1" max="1" chance="0.00780" />		<!-- Камень Жизни Высокого Качества - Уровень 67 -->
			<item id="8760" min="1" max="1" chance="0.00160" />		<!-- Камень Жизни Высшего Качества - Уровень 67 -->
			<item id="1343" min="10" max="30" chance="39.94320" />		<!-- Серебряная Стрела -->
		</category>
	</droplist>
	<spoillist>
			<item id="5448" min="1" max="1" chance="0.02520" />		<!-- Рецепт - Душегуб (60%) -->
			<item id="5494" min="1" max="1" chance="1.42650" />		<!-- Часть Запечатанного Щита Кристалла Тьмы -->
			<item id="729" min="1" max="1" chance="0.00750" />		<!-- Свиток: Модифицировать Оружие (А) -->
	</spoillist>
</npc>
</list>
