<?xml version="1.0" encoding="UTF-8"?>
<list xmlns:xsi="http://www.w3.org/2001/XMLSchema-instance" xsi:noNamespaceSchemaLocation="../../../xsd/DropListData.xsd">
<!-- Смотритель Сада -->
<npc id="22952">
	<droplist>
		<category id="1" chance="70.000">
			<item id="57" min="14828" max="34587" chance="100.00000" />		<!-- Адена -->
		</category>
		<category id="2" chance="12.749">
			<item id="18151" min="1" max="1" chance="2.35313" />		<!-- Неопознанный Шлем Ада -->
			<item id="18166" min="1" max="1" chance="2.35313" />		<!-- Неопознанные Ботинки Ада -->
			<item id="19217" min="1" max="3" chance="60.86752" />		<!-- Материал Неопознанного Шлема Ада -->
			<item id="19232" min="4" max="12" chance="34.42623" />		<!-- Материал Неопознанных Ботинок Ада -->
		</category>
		<category id="3" chance="1.500">
			<item id="17527" min="1" max="1" chance="50.00000" />		<!-- Свиток: Модифицировать Доспех (R) -->
			<item id="19370" min="1" max="1" chance="50.00000" />		<!-- Рецепт - Неопознанная Туника Ада (60%) -->
		</category>
	</droplist>
	<spoillist>
			<item id="19234" min="1" max="5" chance="0.75000" />		<!-- Камень Неопознанного Ожерелья Ада -->
	</spoillist>
</npc>
</list>
