<?xml version="1.0" encoding="UTF-8"?>
<list xmlns:xsi="http://www.w3.org/2001/XMLSchema-instance" xsi:noNamespaceSchemaLocation="../../../xsd/DropListData.xsd">
<!-- Чумной Жук -->
<npc id="23165">
	<droplist>
		<category id="1" chance="70.000">
			<item id="57" min="123" max="286" chance="100.00000" />		<!-- Адена -->
		</category>
		<category id="2" chance="0.030">
			<item id="18121" min="1" max="1" chance="100.00000" />		<!-- Неопознанные Сапоги Бессмертия -->
		</category>
		<category id="3" chance="0.076">
			<item id="19330" min="1" max="1" chance="98.81423" />		<!-- Рецепт - Неопознанные Рукавицы Бессмертия (60%) -->
			<item id="17526" min="1" max="1" chance="1.18577" />		<!-- Свиток: Модифицировать Оружие (R) -->
		</category>
	</droplist>
</npc>
</list>
