<?xml version="1.0" encoding="UTF-8"?>
<!DOCTYPE list SYSTEM "restoration_info.dtd">
<!--By Bonux-->
<list>
	<restoration skill_id="12600" skill_level="1" name="Check Item" consume_item_id="31991">
		<!--Item: ID[31991, NAME[Unidentified Blinzlasher]-->
		<group chance="4.0">
			<item id="9264" min_count="1" max_count="1"/>	<!--Blinzlasher-->
		</group>
		<group chance="32.0">
			<item id="31182" min_count="1" max_count="1"/>	<!--Bound Blinzlasher - Guidance-->
		</group>
		<group chance="32.0">
			<item id="31183" min_count="1" max_count="1"/>	<!--Bound Blinzlasher - Focus-->
		</group>
		<group chance="32.0">
			<item id="31184" min_count="1" max_count="1"/>	<!--Bound Blinzlasher - Critical Damage-->
		</group>
	</restoration>
	<restoration skill_id="12601" skill_level="1" name="Check Item" consume_item_id="31992">
		<!--Item: ID[31992, NAME[Unidentified Blinzlasher]-->
		<group chance="4.0">
			<item id="9264" min_count="1" max_count="1"/>	<!--Blinzlasher-->
		</group>
		<group chance="32.0">
			<item id="31182" min_count="1" max_count="1"/>	<!--Bound Blinzlasher - Guidance-->
		</group>
		<group chance="32.0">
			<item id="31183" min_count="1" max_count="1"/>	<!--Bound Blinzlasher - Focus-->
		</group>
		<group chance="32.0">
			<item id="31184" min_count="1" max_count="1"/>	<!--Bound Blinzlasher - Critical Damage-->
		</group>
	</restoration>
	<restoration skill_id="12602" skill_level="1" name="Check Item" consume_item_id="31993">
		<!--Item: ID[31993, NAME[Unidentified Blast Plate]-->
		<group chance="4.0">
			<item id="351" min_count="1" max_count="1"/>	<!--Blast Plate-->
		</group>
		<group chance="96.0">
			<item id="31197" min_count="1" max_count="1"/>	<!--Bound Blast Plate-->
		</group>
	</restoration>
	<restoration skill_id="12603" skill_level="1" name="Check Item" consume_item_id="31994">
		<!--Item: ID[31994, NAME[Unidentified Bloody Orchid]-->
		<group chance="4.0">
			<item id="235" min_count="1" max_count="1"/>	<!--Bloody Orchid-->
		</group>
		<group chance="32.0">
			<item id="31199" min_count="1" max_count="1"/>	<!--Bound Bloody Orchid - Focus-->
		</group>
		<group chance="32.0">
			<item id="31200" min_count="1" max_count="1"/>	<!--Bound Bloody Orchid - Back Blow-->
		</group>
		<group chance="32.0">
			<item id="31201" min_count="1" max_count="1"/>	<!--Bound Bloody Orchid - Critical Bleed-->
		</group>
	</restoration>
	<restoration skill_id="12604" skill_level="1" name="Check Item" consume_item_id="31995">
		<!--Item: ID[31995, NAME[Unidentified Blood Tornado]-->
		<group chance="4.0">
			<item id="269" min_count="1" max_count="1"/>	<!--Blood Tornado-->
		</group>
		<group chance="32.0">
			<item id="31203" min_count="1" max_count="1"/>	<!--Bound Blood Tornado - Haste-->
		</group>
		<group chance="32.0">
			<item id="31204" min_count="1" max_count="1"/>	<!--Bound Blood Tornado - Focus-->
		</group>
		<group chance="32.0">
			<item id="31205" min_count="1" max_count="1"/>	<!--Bound Blood Tornado - Anger-->
		</group>
	</restoration>
	<restoration skill_id="12605" skill_level="1" name="Check Item" consume_item_id="31996">
		<!--Item: ID[31996, NAME[Unidentified Brigandine Helmet]-->
		<group chance="4.0">
			<item id="2411" min_count="1" max_count="1"/>	<!--Brigandine Helmet-->
		</group>
		<group chance="96.0">
			<item id="31206" min_count="1" max_count="1"/>	<!--Bound Brigandine Helmet-->
		</group>
	</restoration>
	<restoration skill_id="12606" skill_level="1" name="Check Item" consume_item_id="31997">
		<!--Item: ID[31997, NAME[Unidentified Brigandine Shield]-->
		<group chance="4.0">
			<item id="2493" min_count="1" max_count="1"/>	<!--Brigandine Shield-->
		</group>
		<group chance="96.0">
			<item id="31207" min_count="1" max_count="1"/>	<!--Bound Brigandine Shield-->
		</group>
	</restoration>
	<restoration skill_id="12607" skill_level="1" name="Check Item" consume_item_id="31998">
		<!--Item: ID[31998, NAME[Unidentified Brigandine Boots]-->
		<group chance="4.0">
			<item id="2425" min_count="1" max_count="1"/>	<!--Brigandine Boots-->
		</group>
		<group chance="96.0">
			<item id="31208" min_count="1" max_count="1"/>	<!--Bound Brigandine Boots-->
		</group>
	</restoration>
	<restoration skill_id="12608" skill_level="1" name="Check Item" consume_item_id="31999">
		<!--Item: ID[31999, NAME[Unidentified Brigandine Gauntlet]-->
		<group chance="4.0">
			<item id="2449" min_count="1" max_count="1"/>	<!--Brigandine Gauntlets-->
		</group>
		<group chance="96.0">
			<item id="31209" min_count="1" max_count="1"/>	<!--Bound Brigandine Gauntlets-->
		</group>
	</restoration>
	<restoration skill_id="12609" skill_level="1" name="Check Item" consume_item_id="32000">
		<!--Item: ID[32000, NAME[Unidentified Brigandine Gaiters]-->
		<group chance="4.0">
			<item id="2378" min_count="1" max_count="1"/>	<!--Brigandine Gaiters-->
		</group>
		<group chance="96.0">
			<item id="31210" min_count="1" max_count="1"/>	<!--Bound Brigandine Gaiters-->
		</group>
	</restoration>
	<restoration skill_id="12610" skill_level="1" name="Check Item" consume_item_id="32001">
		<!--Item: ID[32001, NAME[Unidentified Brigandine]-->
		<group chance="4.0">
			<item id="352" min_count="1" max_count="1"/>	<!--Brigandine-->
		</group>
		<group chance="96.0">
			<item id="31211" min_count="1" max_count="1"/>	<!--Bound Brigandine-->
		</group>
	</restoration>
	<restoration skill_id="12611" skill_level="1" name="Check Item" consume_item_id="32002">
		<!--Item: ID[32002, NAME[Unidentified Gloves of Seal]-->
		<group chance="4.0">
			<item id="2457" min_count="1" max_count="1"/>	<!--Gloves of Seal-->
		</group>
		<group chance="96.0">
			<item id="31212" min_count="1" max_count="1"/>	<!--Bound Gloves of Seal-->
		</group>
	</restoration>
	<restoration skill_id="12612" skill_level="1" name="Check Item" consume_item_id="32003">
		<!--Item: ID[32003, NAME[Unidentified Boots of Seal]-->
		<group chance="4.0">
			<item id="2433" min_count="1" max_count="1"/>	<!--Boots of Seal-->
		</group>
		<group chance="96.0">
			<item id="31213" min_count="1" max_count="1"/>	<!--Bound Boots of Seal-->
		</group>
	</restoration>
	<restoration skill_id="12613" skill_level="1" name="Check Item" consume_item_id="32004">
		<!--Item: ID[32004, NAME[Unidentified Ring of Seal]-->
		<group chance="4.0">
			<item id="14344" min_count="1" max_count="1"/>	<!--Ring of Seal-->
		</group>
		<group chance="96.0">
			<item id="31214" min_count="1" max_count="1"/>	<!--Bound Ring of Seal-->
		</group>
	</restoration>
	<restoration skill_id="12614" skill_level="1" name="Check Item" consume_item_id="32005">
		<!--Item: ID[32005, NAME[Unidentified Necklace of Seal]-->
		<group chance="4.0">
			<item id="14342" min_count="1" max_count="1"/>	<!--Necklace of Seal-->
		</group>
		<group chance="96.0">
			<item id="31215" min_count="1" max_count="1"/>	<!--Bound Necklace of Seal-->
		</group>
	</restoration>
	<restoration skill_id="12615" skill_level="1" name="Check Item" consume_item_id="32006">
		<!--Item: ID[32006, NAME[Unidentified Robe of Seal]-->
		<group chance="4.0">
			<item id="440" min_count="1" max_count="1"/>	<!--Robe of Seal-->
		</group>
		<group chance="96.0">
			<item id="31216" min_count="1" max_count="1"/>	<!--Bound Robe of Seal-->
		</group>
	</restoration>
	<restoration skill_id="12616" skill_level="1" name="Check Item" consume_item_id="32007">
		<!--Item: ID[32007, NAME[Unidentified Earring of Seal]-->
		<group chance="4.0">
			<item id="854" min_count="1" max_count="1"/>	<!--Earring of Seal-->
		</group>
		<group chance="96.0">
			<item id="31217" min_count="1" max_count="1"/>	<!--Bound Earring of Seal-->
		</group>
	</restoration>
	<restoration skill_id="12617" skill_level="1" name="Check Item" consume_item_id="32008">
		<!--Item: ID[32008, NAME[Unidentified Earring of Seal]-->
		<group chance="4.0">
			<item id="854" min_count="1" max_count="1"/>	<!--Earring of Seal-->
		</group>
		<group chance="96.0">
			<item id="31217" min_count="1" max_count="1"/>	<!--Bound Earring of Seal-->
		</group>
	</restoration>
	<restoration skill_id="12618" skill_level="1" name="Check Item" consume_item_id="32009">
		<!--Item: ID[32009, NAME[Unidentified Bonebreaker]-->
		<group chance="4.0">
			<item id="159" min_count="1" max_count="1"/>	<!--Bonebreaker-->
		</group>
		<group chance="96.0">
			<item id="31219" min_count="1" max_count="1"/>	<!--Bound Bonebreaker-->
		</group>
	</restoration>
	<restoration skill_id="12619" skill_level="1" name="Check Item" consume_item_id="32010">
		<!--Item: ID[32010, NAME[Unidentified Proof of Revenge]-->
		<group chance="4.0">
			<item id="314" min_count="1" max_count="1"/>	<!--Proof of Revenge-->
		</group>
		<group chance="96.0">
			<item id="31220" min_count="1" max_count="1"/>	<!--Bound Proof of Revenge-->
		</group>
	</restoration>
	<restoration skill_id="12620" skill_level="1" name="Check Item" consume_item_id="32011">
		<!--Item: ID[32011, NAME[Unidentified Bellion Cestus]-->
		<group chance="4.0">
			<item id="14316" min_count="1" max_count="1"/>	<!--Bellion Cestus-->
		</group>
		<group chance="32.0">
			<item id="31222" min_count="1" max_count="1"/>	<!--Bound Bellion Cestus - Critical Drain-->
		</group>
		<group chance="32.0">
			<item id="31223" min_count="1" max_count="1"/>	<!--Bound Bellion Cestus - Critical Poison-->
		</group>
		<group chance="32.0">
			<item id="31224" min_count="1" max_count="1"/>	<!--Bound Bellion Cestus - Rsk. Haste-->
		</group>
	</restoration>
	<restoration skill_id="12621" skill_level="1" name="Check Item" consume_item_id="32012">
		<!--Item: ID[32012, NAME[Unidentified Berserker Blade]-->
		<group chance="4.0">
			<item id="14302" min_count="1" max_count="1"/>	<!--Berserker Blade-->
		</group>
		<group chance="32.0">
			<item id="31226" min_count="1" max_count="1"/>	<!--Bound Berserker Blade - Focus-->
		</group>
		<group chance="32.0">
			<item id="31227" min_count="1" max_count="1"/>	<!--Bound Berserker Blade - Critical Damage-->
		</group>
		<group chance="32.0">
			<item id="31228" min_count="1" max_count="1"/>	<!--Bound Berserker Blade - Haste-->
		</group>
	</restoration>
	<restoration skill_id="12622" skill_level="1" name="Check Item" consume_item_id="32013">
		<!--Item: ID[32013, NAME[Unidentified Battle Axe]-->
		<group chance="4.0">
			<item id="160" min_count="1" max_count="1"/>	<!--Battle Axe-->
		</group>
		<group chance="32.0">
			<item id="31230" min_count="1" max_count="1"/>	<!--Bound Battle Axe - Anger-->
		</group>
		<group chance="32.0">
			<item id="31231" min_count="1" max_count="1"/>	<!--Bound Battle Axe - Rsk. Focus-->
		</group>
		<group chance="32.0">
			<item id="31232" min_count="1" max_count="1"/>	<!--Bound Battle Axe - Haste-->
		</group>
	</restoration>
	<restoration skill_id="12623" skill_level="1" name="Check Item" consume_item_id="32014">
		<!--Item: ID[32014, NAME[Unidentified Bec de Corbin]-->
		<group chance="4.0">
			<item id="94" min_count="1" max_count="1"/>	<!--Bec de Corbin-->
		</group>
		<group chance="32.0">
			<item id="31234" min_count="1" max_count="1"/>	<!--Bound Bec de Corbin - Critical Stun-->
		</group>
		<group chance="32.0">
			<item id="31235" min_count="1" max_count="1"/>	<!--Bound Bec de Corbin - Long Blow-->
		</group>
		<group chance="32.0">
			<item id="31236" min_count="1" max_count="1"/>	<!--Bound Bec de Corbin - Light-->
		</group>
	</restoration>
	<restoration skill_id="12624" skill_level="1" name="Check Item" consume_item_id="32015">
		<!--Item: ID[32015, NAME[Unidentified Ballista]-->
		<group chance="4.0">
			<item id="9256" min_count="1" max_count="1"/>	<!--Ballista-->
		</group>
		<group chance="32.0">
			<item id="31239" min_count="1" max_count="1"/>	<!--Bound Ballista - Guidance-->
		</group>
		<group chance="32.0">
			<item id="31240" min_count="1" max_count="1"/>	<!--Bound Ballista - Miser-->
		</group>
		<group chance="32.0">
			<item id="31241" min_count="1" max_count="1"/>	<!--Bound Ballista - Quick Recovery-->
		</group>
	</restoration>
	<restoration skill_id="12625" skill_level="1" name="Check Item" consume_item_id="32016">
		<!--Item: ID[32016, NAME[Unidentified Ballista]-->
		<group chance="4.0">
			<item id="9256" min_count="1" max_count="1"/>	<!--Ballista-->
		</group>
		<group chance="32.0">
			<item id="31239" min_count="1" max_count="1"/>	<!--Bound Ballista - Guidance-->
		</group>
		<group chance="32.0">
			<item id="31240" min_count="1" max_count="1"/>	<!--Bound Ballista - Miser-->
		</group>
		<group chance="32.0">
			<item id="31241" min_count="1" max_count="1"/>	<!--Bound Ballista - Quick Recovery-->
		</group>
	</restoration>
	<restoration skill_id="12626" skill_level="1" name="Check Item" consume_item_id="32017">
		<!--Item: ID[32017, NAME[Unidentified Bastard Sword*Sword of Revolution]-->
		<group chance="4.0">
			<item id="2531" min_count="1" max_count="1"/>	<!--Bastard Sword*Sword of Revolution-->
		</group>
		<group chance="96.0">
			<item id="31245" min_count="1" max_count="1"/>	<!--Bound Bastard Sword*Sword of Revolution-->
		</group>
	</restoration>
	<restoration skill_id="12627" skill_level="1" name="Check Item" consume_item_id="32018">
		<!--Item: ID[32018, NAME[Unidentified Bastard Sword*Crimson Sword]-->
		<group chance="4.0">
			<item id="2529" min_count="1" max_count="1"/>	<!--Bastard Sword*Crimson Sword-->
		</group>
		<group chance="96.0">
			<item id="31246" min_count="1" max_count="1"/>	<!--Bound Bastard Sword*Crimson Sword-->
		</group>
	</restoration>
	<restoration skill_id="12628" skill_level="1" name="Check Item" consume_item_id="32019">
		<!--Item: ID[32019, NAME[Unidentified Bastard Sword*Artisan's Sword]-->
		<group chance="4.0">
			<item id="2527" min_count="1" max_count="1"/>	<!--Bastard Sword*Artisan's Sword-->
		</group>
		<group chance="96.0">
			<item id="31247" min_count="1" max_count="1"/>	<!--Bound Bastard Sword*Artisan's Sword-->
		</group>
	</restoration>
	<restoration skill_id="12629" skill_level="1" name="Check Item" consume_item_id="32020">
		<!--Item: ID[32020, NAME[Unidentified Bastard Sword*Elven Sword]-->
		<group chance="4.0">
			<item id="2530" min_count="1" max_count="1"/>	<!--Bastard Sword*Elven Sword-->
		</group>
		<group chance="96.0">
			<item id="31248" min_count="1" max_count="1"/>	<!--Bound Bastard Sword*Elven Sword-->
		</group>
	</restoration>
	<restoration skill_id="12630" skill_level="1" name="Check Item" consume_item_id="32021">
		<!--Item: ID[32021, NAME[Unidentified Bastard Sword*Elven Long Sword]-->
		<group chance="4.0">
			<item id="2532" min_count="1" max_count="1"/>	<!--Bastard Sword*Elven Long Sword-->
		</group>
		<group chance="96.0">
			<item id="31249" min_count="1" max_count="1"/>	<!--Bound Bastard Sword*Elven Long Sword-->
		</group>
	</restoration>
	<restoration skill_id="12631" skill_level="1" name="Check Item" consume_item_id="32022">
		<!--Item: ID[32022, NAME[Unidentified Bastard Sword*Spinebone Sword]-->
		<group chance="4.0">
			<item id="2526" min_count="1" max_count="1"/>	<!--Bastard Sword*Spinebone Sword-->
		</group>
		<group chance="96.0">
			<item id="31250" min_count="1" max_count="1"/>	<!--Bound Bastard Sword*Spinebone Sword-->
		</group>
	</restoration>
	<restoration skill_id="12632" skill_level="1" name="Check Item" consume_item_id="32023">
		<!--Item: ID[32023, NAME[Unidentified Bastard Sword*Bastard Sword]-->
		<group chance="4.0">
			<item id="2525" min_count="1" max_count="1"/>	<!--Bastard Sword*Bastard Sword-->
		</group>
		<group chance="96.0">
			<item id="31251" min_count="1" max_count="1"/>	<!--Bound Bastard Sword*Bastard Sword-->
		</group>
	</restoration>
	<restoration skill_id="12633" skill_level="1" name="Check Item" consume_item_id="32024">
		<!--Item: ID[32024, NAME[Unidentified Bastard Sword*Knight's Sword]-->
		<group chance="4.0">
			<item id="2528" min_count="1" max_count="1"/>	<!--Bastard Sword*Knight's Sword-->
		</group>
		<group chance="96.0">
			<item id="31252" min_count="1" max_count="1"/>	<!--Bound Bastard Sword*Knight's Sword-->
		</group>
	</restoration>
	<restoration skill_id="12634" skill_level="1" name="Check Item" consume_item_id="32025">
		<!--Item: ID[32025, NAME[Unidentified Bastard Sword]-->
		<group chance="4.0">
			<item id="69" min_count="1" max_count="1"/>	<!--Bastard Sword-->
		</group>
		<group chance="96.0">
			<item id="31253" min_count="1" max_count="1"/>	<!--Bound Bastard Sword-->
		</group>
	</restoration>
	<restoration skill_id="12635" skill_level="1" name="Check Item" consume_item_id="32026">
		<!--Item: ID[32026, NAME[Unidentified Basalt Battlehammer]-->
		<group chance="4.0">
			<item id="6365" min_count="1" max_count="1"/>	<!--Basalt Battlehammer-->
		</group>
		<group chance="32.0">
			<item id="31255" min_count="1" max_count="1"/>	<!--Bound Basalt Battlehammer - HP Drain-->
		</group>
		<group chance="32.0">
			<item id="31256" min_count="1" max_count="1"/>	<!--Bound Basalt Battlehammer - Health-->
		</group>
		<group chance="32.0">
			<item id="31257" min_count="1" max_count="1"/>	<!--Bound Basalt Battlehammer - HP Regeneration-->
		</group>
	</restoration>
	<restoration skill_id="12636" skill_level="1" name="Check Item" consume_item_id="32027">
		<!--Item: ID[32027, NAME[Unidentified Body Slasher]-->
		<group chance="4.0">
			<item id="302" min_count="1" max_count="1"/>	<!--Body Slasher-->
		</group>
		<group chance="32.0">
			<item id="31259" min_count="1" max_count="1"/>	<!--Bound Body Slasher - Critical Stun-->
		</group>
		<group chance="32.0">
			<item id="31260" min_count="1" max_count="1"/>	<!--Bound Body Slasher - Long Blow-->
		</group>
		<group chance="32.0">
			<item id="31261" min_count="1" max_count="1"/>	<!--Bound Body Slasher - Wide Blow-->
		</group>
	</restoration>
	<restoration skill_id="12637" skill_level="1" name="Check Item" consume_item_id="32028">
		<!--Item: ID[32028, NAME[Unidentified Bagh-Nakh]-->
		<group chance="4.0">
			<item id="258" min_count="1" max_count="1"/>	<!--Bagh-Nakh-->
		</group>
		<group chance="96.0">
			<item id="31262" min_count="1" max_count="1"/>	<!--Bound Bagh-Nakh-->
		</group>
	</restoration>
	<restoration skill_id="12638" skill_level="1" name="Check Item" consume_item_id="32029">
		<!--Item: ID[32029, NAME[Unidentified Sword of Delusion]-->
		<group chance="4.0">
			<item id="76" min_count="1" max_count="1"/>	<!--Sword of Delusion-->
		</group>
		<group chance="32.0">
			<item id="31264" min_count="1" max_count="1"/>	<!--Bound Sword of Delusion - Focus-->
		</group>
		<group chance="32.0">
			<item id="31265" min_count="1" max_count="1"/>	<!--Bound Sword of Delusion - Health-->
		</group>
		<group chance="32.0">
			<item id="31266" min_count="1" max_count="1"/>	<!--Bound Sword of Delusion - Rsk. Haste-->
		</group>
	</restoration>
	<restoration skill_id="12639" skill_level="1" name="Check Item" consume_item_id="32030">
		<!--Item: ID[32030, NAME[Unidentified Meteor Shower]-->
		<group chance="4.0">
			<item id="2504" min_count="1" max_count="1"/>	<!--Meteor Shower-->
		</group>
		<group chance="32.0">
			<item id="31268" min_count="1" max_count="1"/>	<!--Bound Meteor Shower - Focus-->
		</group>
		<group chance="32.0">
			<item id="31269" min_count="1" max_count="1"/>	<!--Bound Meteor Shower - Critical Bleed-->
		</group>
		<group chance="32.0">
			<item id="31270" min_count="1" max_count="1"/>	<!--Bound Meteor Shower - Rsk. Haste-->
		</group>
	</restoration>
	<restoration skill_id="12640" skill_level="1" name="Check Item" consume_item_id="32031">
		<!--Item: ID[32031, NAME[Unidentified Mystic Staff]-->
		<group chance="4.0">
			<item id="183" min_count="1" max_count="1"/>	<!--Mystic Staff-->
		</group>
		<group chance="96.0">
			<item id="31271" min_count="1" max_count="1"/>	<!--Bound Mystic Staff-->
		</group>
	</restoration>
	<restoration skill_id="12641" skill_level="1" name="Check Item" consume_item_id="32032">
		<!--Item: ID[32032, NAME[Unidentified Mystic Knife]-->
		<group chance="4.0">
			<item id="239" min_count="1" max_count="1"/>	<!--Mystic Knife-->
		</group>
		<group chance="96.0">
			<item id="31272" min_count="1" max_count="1"/>	<!--Bound Mystic Knife-->
		</group>
	</restoration>
	<restoration skill_id="12642" skill_level="1" name="Check Item" consume_item_id="32033">
		<!--Item: ID[32033, NAME[Unidentified Mysterious Sword]-->
		<group chance="4.0">
			<item id="7887" min_count="1" max_count="1"/>	<!--Mysterious Sword-->
		</group>
		<group chance="32.0">
			<item id="31274" min_count="1" max_count="1"/>	<!--Bound Mysterious Sword - Acumen-->
		</group>
		<group chance="32.0">
			<item id="31275" min_count="1" max_count="1"/>	<!--Bound Mysterious Sword - M. Atk.-->
		</group>
		<group chance="32.0">
			<item id="31276" min_count="1" max_count="1"/>	<!--Bound Mysterious Sword - Magic Weakness-->
		</group>
	</restoration>
	<restoration skill_id="12643" skill_level="1" name="Check Item" consume_item_id="32034">
		<!--Item: ID[32034, NAME[Unidentified Mithril Breastplate]-->
		<group chance="4.0">
			<item id="58" min_count="1" max_count="1"/>	<!--Mithril Breastplate-->
		</group>
		<group chance="96.0">
			<item id="31277" min_count="1" max_count="1"/>	<!--Bound Mithril Breastplate-->
		</group>
	</restoration>
	<restoration skill_id="12644" skill_level="1" name="Check Item" consume_item_id="32035">
		<!--Item: ID[32035, NAME[Unidentified Mithril Stockings]-->
		<group chance="4.0">
			<item id="470" min_count="1" max_count="1"/>	<!--Mithril Stockings-->
		</group>
		<group chance="96.0">
			<item id="31278" min_count="1" max_count="1"/>	<!--Bound Mithril Stockings-->
		</group>
	</restoration>
	<restoration skill_id="12645" skill_level="1" name="Check Item" consume_item_id="32036">
		<!--Item: ID[32036, NAME[Unidentified Mithril Stockings]-->
		<group chance="4.0">
			<item id="470" min_count="1" max_count="1"/>	<!--Mithril Stockings-->
		</group>
		<group chance="96.0">
			<item id="31278" min_count="1" max_count="1"/>	<!--Bound Mithril Stockings-->
		</group>
	</restoration>
	<restoration skill_id="12646" skill_level="1" name="Check Item" consume_item_id="32037">
		<!--Item: ID[32037, NAME[Unidentified Mithril Tunic]-->
		<group chance="4.0">
			<item id="437" min_count="1" max_count="1"/>	<!--Mithril Tunic-->
		</group>
		<group chance="96.0">
			<item id="31280" min_count="1" max_count="1"/>	<!--Bound Mithril Tunic-->
		</group>
	</restoration>
	<restoration skill_id="12647" skill_level="1" name="Check Item" consume_item_id="32038">
		<!--Item: ID[32038, NAME[Unidentified Mithril Tunic]-->
		<group chance="4.0">
			<item id="437" min_count="1" max_count="1"/>	<!--Mithril Tunic-->
		</group>
		<group chance="96.0">
			<item id="31280" min_count="1" max_count="1"/>	<!--Bound Mithril Tunic-->
		</group>
	</restoration>
	<restoration skill_id="12648" skill_level="1" name="Check Item" consume_item_id="32039">
		<!--Item: ID[32039, NAME[Unidentified Mithril Gloves]-->
		<group chance="4.0">
			<item id="61" min_count="1" max_count="1"/>	<!--Mithril Plate Gloves-->
		</group>
		<group chance="96.0">
			<item id="31282" min_count="1" max_count="1"/>	<!--Bound Mithril Gloves-->
		</group>
	</restoration>
	<restoration skill_id="12649" skill_level="1" name="Check Item" consume_item_id="32040">
		<!--Item: ID[32040, NAME[Unidentified Mithril Gloves]-->
		<group chance="4.0">
			<item id="61" min_count="1" max_count="1"/>	<!--Mithril Plate Gloves-->
		</group>
		<group chance="96.0">
			<item id="31282" min_count="1" max_count="1"/>	<!--Bound Mithril Gloves-->
		</group>
	</restoration>
	<restoration skill_id="12650" skill_level="1" name="Check Item" consume_item_id="32041">
		<!--Item: ID[32041, NAME[Unidentified Mithril Scale Gaiters]-->
		<group chance="4.0">
			<item id="2377" min_count="1" max_count="1"/>	<!--Mithril Scale Gaiters-->
		</group>
		<group chance="96.0">
			<item id="31284" min_count="1" max_count="1"/>	<!--Bound Mithril Scale Gaiters-->
		</group>
	</restoration>
	<restoration skill_id="12651" skill_level="1" name="Check Item" consume_item_id="32042">
		<!--Item: ID[32042, NAME[Unidentified Mithril Banded Mail]-->
		<group chance="4.0">
			<item id="393" min_count="1" max_count="1"/>	<!--Mithril Banded Mail-->
		</group>
		<group chance="96.0">
			<item id="31285" min_count="1" max_count="1"/>	<!--Bound Mithril Banded Mail-->
		</group>
	</restoration>
	<restoration skill_id="12652" skill_level="1" name="Check Item" consume_item_id="32043">
		<!--Item: ID[32043, NAME[Unidentified Mithril Banded Gaiters]-->
		<group chance="4.0">
			<item id="415" min_count="1" max_count="1"/>	<!--Mithril Banded Gaiters-->
		</group>
		<group chance="96.0">
			<item id="31286" min_count="1" max_count="1"/>	<!--Bound Mithril Banded Gaiters-->
		</group>
	</restoration>
	<restoration skill_id="12653" skill_level="1" name="Check Item" consume_item_id="32044">
		<!--Item: ID[32044, NAME[Unidentified Mithril Ring]-->
		<group chance="4.0">
			<item id="882" min_count="1" max_count="1"/>	<!--Mithril Ring-->
		</group>
		<group chance="96.0">
			<item id="31287" min_count="1" max_count="1"/>	<!--Bound Mithril Ring-->
		</group>
	</restoration>
	<restoration skill_id="12654" skill_level="1" name="Check Item" consume_item_id="32045">
		<!--Item: ID[32045, NAME[Unidentified Mithril Dagger]-->
		<group chance="4.0">
			<item id="225" min_count="1" max_count="1"/>	<!--Mithril Dagger-->
		</group>
		<group chance="96.0">
			<item id="31288" min_count="1" max_count="1"/>	<!--Bound Mithril Dagger-->
		</group>
	</restoration>
	<restoration skill_id="12655" skill_level="1" name="Check Item" consume_item_id="32046">
		<!--Item: ID[32046, NAME[Unidentified Mithril Gauntlets]-->
		<group chance="4.0">
			<item id="608" min_count="1" max_count="1"/>	<!--Mithril Gauntlets-->
		</group>
		<group chance="96.0">
			<item id="31289" min_count="1" max_count="1"/>	<!--Bound Mithril Gauntlets-->
		</group>
	</restoration>
	<restoration skill_id="12656" skill_level="1" name="Check Item" consume_item_id="32047">
		<!--Item: ID[32047, NAME[Unidentified Mithril Gaiters]-->
		<group chance="4.0">
			<item id="59" min_count="1" max_count="1"/>	<!--Mithril Gaiters-->
		</group>
		<group chance="96.0">
			<item id="31290" min_count="1" max_count="1"/>	<!--Bound Mithril Gaiters-->
		</group>
	</restoration>
	<restoration skill_id="12657" skill_level="1" name="Check Item" consume_item_id="32048">
		<!--Item: ID[32048, NAME[Unidentified Moonstone Earring]-->
		<group chance="4.0">
			<item id="852" min_count="1" max_count="1"/>	<!--Moonstone Earring-->
		</group>
		<group chance="96.0">
			<item id="31291" min_count="1" max_count="1"/>	<!--Bound Moonstone Earring-->
		</group>
	</restoration>
	<restoration skill_id="12658" skill_level="1" name="Check Item" consume_item_id="32049">
		<!--Item: ID[32049, NAME[Unidentified Moonstone Earring]-->
		<group chance="4.0">
			<item id="852" min_count="1" max_count="1"/>	<!--Moonstone Earring-->
		</group>
		<group chance="96.0">
			<item id="31291" min_count="1" max_count="1"/>	<!--Bound Moonstone Earring-->
		</group>
	</restoration>
	<restoration skill_id="12659" skill_level="1" name="Check Item" consume_item_id="32050">
		<!--Item: ID[32050, NAME[Unidentified Linen Shirt]-->
		<group chance="4.0">
			<item id="9578" min_count="1" max_count="1"/>	<!--Linen Shirt-->
		</group>
		<group chance="96.0">
			<item id="31293" min_count="1" max_count="1"/>	<!--Bound Linen Shirt-->
		</group>
	</restoration>
	<restoration skill_id="12660" skill_level="1" name="Check Item" consume_item_id="32051">
		<!--Item: ID[32051, NAME[Unidentified Morning Star]-->
		<group chance="4.0">
			<item id="88" min_count="1" max_count="1"/>	<!--Morning Star-->
		</group>
		<group chance="96.0">
			<item id="31294" min_count="1" max_count="1"/>	<!--Bound Morning Star-->
		</group>
	</restoration>
	<restoration skill_id="12661" skill_level="1" name="Check Item" consume_item_id="32052">
		<!--Item: ID[32052, NAME[Unidentified Maingauche]-->
		<group chance="4.0">
			<item id="224" min_count="1" max_count="1"/>	<!--Maingauche-->
		</group>
		<group chance="96.0">
			<item id="31295" min_count="1" max_count="1"/>	<!--Bound Maingauche-->
		</group>
	</restoration>
	<restoration skill_id="12662" skill_level="1" name="Check Item" consume_item_id="32053">
		<!--Item: ID[32053, NAME[Unidentified Major Arcana Circlet]-->
		<group chance="4.0">
			<item id="6386" min_count="1" max_count="1"/>	<!--Major Arcana Circlet-->
		</group>
		<group chance="96.0">
			<item id="31296" min_count="1" max_count="1"/>	<!--Bound Major Arcana Circlet-->
		</group>
	</restoration>
	<restoration skill_id="12663" skill_level="1" name="Check Item" consume_item_id="32054">
		<!--Item: ID[32054, NAME[Unidentified Major Arcana Boots]-->
		<group chance="4.0">
			<item id="6385" min_count="1" max_count="1"/>	<!--Major Arcana Boots-->
		</group>
		<group chance="96.0">
			<item id="31297" min_count="1" max_count="1"/>	<!--Bound Major Arcana Boots-->
		</group>
	</restoration>
	<restoration skill_id="12664" skill_level="1" name="Check Item" consume_item_id="32055">
		<!--Item: ID[32055, NAME[Unidentified Major Arcana Robe]-->
		<group chance="4.0">
			<item id="6383" min_count="1" max_count="1"/>	<!--Major Arcana Robe-->
		</group>
		<group chance="96.0">
			<item id="31298" min_count="1" max_count="1"/>	<!--Bound Major Arcana Robe-->
		</group>
	</restoration>
	<restoration skill_id="12665" skill_level="1" name="Check Item" consume_item_id="32056">
		<!--Item: ID[32056, NAME[Unidentified Major Arcana Gloves]-->
		<group chance="4.0">
			<item id="6384" min_count="1" max_count="1"/>	<!--Major Arcana Gloves-->
		</group>
		<group chance="96.0">
			<item id="31299" min_count="1" max_count="1"/>	<!--Bound Major Arcana Gloves-->
		</group>
	</restoration>
	<restoration skill_id="12666" skill_level="1" name="Check Item" consume_item_id="32057">
		<!--Item: ID[32057, NAME[Unidentified Mace of Underworld]-->
		<group chance="4.0">
			<item id="202" min_count="1" max_count="1"/>	<!--Mace of Underworld-->
		</group>
		<group chance="32.0">
			<item id="31301" min_count="1" max_count="1"/>	<!--Bound Mace of Underworld - Mana Up-->
		</group>
		<group chance="32.0">
			<item id="31302" min_count="1" max_count="1"/>	<!--Bound Mace of Underworld - Magic Silence-->
		</group>
		<group chance="32.0">
			<item id="31303" min_count="1" max_count="1"/>	<!--Bound Mace of Underworld - Conversion-->
		</group>
	</restoration>
	<restoration skill_id="12667" skill_level="1" name="Check Item" consume_item_id="32058">
		<!--Item: ID[32058, NAME[Unidentified Manticore Skin Gloves]-->
		<group chance="4.0">
			<item id="2448" min_count="1" max_count="1"/>	<!--Manticore Skin Gloves-->
		</group>
		<group chance="96.0">
			<item id="31304" min_count="1" max_count="1"/>	<!--Bound Manticore Skin Gloves-->
		</group>
	</restoration>
	<restoration skill_id="12668" skill_level="1" name="Check Item" consume_item_id="32059">
		<!--Item: ID[32059, NAME[Unidentified Manticore Skin Shirt]-->
		<group chance="4.0">
			<item id="395" min_count="1" max_count="1"/>	<!--Manticore Skin Shirt-->
		</group>
		<group chance="96.0">
			<item id="31305" min_count="1" max_count="1"/>	<!--Bound Manticore Skin Shirt-->
		</group>
	</restoration>
	<restoration skill_id="12669" skill_level="1" name="Check Item" consume_item_id="32060">
		<!--Item: ID[32060, NAME[Unidentified Manticore Skin Boots]-->
		<group chance="4.0">
			<item id="2424" min_count="1" max_count="1"/>	<!--Manticore Skin Boots-->
		</group>
		<group chance="96.0">
			<item id="31306" min_count="1" max_count="1"/>	<!--Bound Manticore Skin Boots-->
		</group>
	</restoration>
	<restoration skill_id="12670" skill_level="1" name="Check Item" consume_item_id="32061">
		<!--Item: ID[32061, NAME[Unidentified Manticore Skin Gaiters]-->
		<group chance="4.0">
			<item id="417" min_count="1" max_count="1"/>	<!--Manticore Skin Gaiters-->
		</group>
		<group chance="96.0">
			<item id="31307" min_count="1" max_count="1"/>	<!--Bound Manticore Skin Gaiters-->
		</group>
	</restoration>
	<restoration skill_id="12671" skill_level="1" name="Check Item" consume_item_id="32062">
		<!--Item: ID[32062, NAME[Unidentified Deadman's Staff]-->
		<group chance="4.0">
			<item id="14293" min_count="1" max_count="1"/>	<!--Deadman's Staff-->
		</group>
		<group chance="32.0">
			<item id="31309" min_count="1" max_count="1"/>	<!--Bound Deadman's Staff - Magic Regeneration-->
		</group>
		<group chance="32.0">
			<item id="31310" min_count="1" max_count="1"/>	<!--Bound Deadman's Staff - Mental Shield-->
		</group>
		<group chance="32.0">
			<item id="31311" min_count="1" max_count="1"/>	<!--Bound Deadman's Staff - Magic Hold-->
		</group>
	</restoration>
	<restoration skill_id="12672" skill_level="1" name="Check Item" consume_item_id="32063">
		<!--Item: ID[32063, NAME[Unidentified Majestic Plate Armor]-->
		<group chance="4.0">
			<item id="2383" min_count="1" max_count="1"/>	<!--Majestic Plate Armor-->
		</group>
		<group chance="96.0">
			<item id="31312" min_count="1" max_count="1"/>	<!--Bound Majestic Plate Armor-->
		</group>
	</restoration>
	<restoration skill_id="12673" skill_level="1" name="Check Item" consume_item_id="32064">
		<!--Item: ID[32064, NAME[Unidentified Majestic Earring]-->
		<group chance="4.0">
			<item id="14348" min_count="1" max_count="1"/>	<!--Majestic Earring-->
		</group>
		<group chance="96.0">
			<item id="31313" min_count="1" max_count="1"/>	<!--Bound Majestic Earring-->
		</group>
	</restoration>
	<restoration skill_id="12674" skill_level="1" name="Check Item" consume_item_id="32065">
		<!--Item: ID[32065, NAME[Unidentified Majestic Circlet]-->
		<group chance="4.0">
			<item id="2419" min_count="1" max_count="1"/>	<!--Majestic Circlet-->
		</group>
		<group chance="96.0">
			<item id="31314" min_count="1" max_count="1"/>	<!--Bound Majestic Circlet-->
		</group>
	</restoration>
	<restoration skill_id="12675" skill_level="1" name="Check Item" consume_item_id="32066">
		<!--Item: ID[32066, NAME[Unidentified Majestic Boots]-->
		<group chance="4.0">
			<item id="583" min_count="1" max_count="1"/>	<!--Majestic Boots-->
		</group>
		<group chance="96.0">
			<item id="32813" min_count="1" max_count="1"/>	<!--Sealed Bound Majestic Boots-->
		</group>
	</restoration>
	<restoration skill_id="12676" skill_level="1" name="Check Item" consume_item_id="32067">
		<!--Item: ID[32067, NAME[Unidentified Majestic Ring]-->
		<group chance="4.0">
			<item id="14349" min_count="1" max_count="1"/>	<!--Majestic Ring-->
		</group>
		<group chance="96.0">
			<item id="31318" min_count="1" max_count="1"/>	<!--Bound Majestic Ring-->
		</group>
	</restoration>
	<restoration skill_id="12677" skill_level="1" name="Check Item" consume_item_id="32068">
		<!--Item: ID[32068, NAME[Unidentified Majestic Robe]-->
		<group chance="4.0">
			<item id="2409" min_count="1" max_count="1"/>	<!--Majestic Robe-->
		</group>
		<group chance="96.0">
			<item id="31319" min_count="1" max_count="1"/>	<!--Bound Majestic Robe-->
		</group>
	</restoration>
	<restoration skill_id="12678" skill_level="1" name="Check Item" consume_item_id="32069">
		<!--Item: ID[32069, NAME[Unidentified Majestic Leather Armor]-->
		<group chance="4.0">
			<item id="2395" min_count="1" max_count="1"/>	<!--Majestic Leather Armor-->
		</group>
		<group chance="96.0">
			<item id="31320" min_count="1" max_count="1"/>	<!--Bound Majestic Leather Armor-->
		</group>
	</restoration>
	<restoration skill_id="12679" skill_level="1" name="Check Item" consume_item_id="32070">
		<!--Item: ID[32070, NAME[Unidentified Majestic Necklace]-->
		<group chance="4.0">
			<item id="14350" min_count="1" max_count="1"/>	<!--Majestic Necklace-->
		</group>
		<group chance="96.0">
			<item id="31321" min_count="1" max_count="1"/>	<!--Bound Majestic Necklace-->
		</group>
	</restoration>
	<restoration skill_id="12680" skill_level="1" name="Check Item" consume_item_id="32071">
		<!--Item: ID[32071, NAME[Unidentified Majestic Gauntlet]-->
		<group chance="4.0">
			<item id="2482" min_count="1" max_count="1"/>	<!--Majestic Gauntlets-->
		</group>
		<group chance="96.0">
			<item id="32809" min_count="1" max_count="1"/>	<!--Sealed Bound Majestic Gauntlet-->
		</group>
	</restoration>
	<restoration skill_id="12681" skill_level="1" name="Check Item" consume_item_id="32072">
		<!--Item: ID[32072, NAME[Unidentified Soulfire Dirk]-->
		<group chance="4.0">
			<item id="242" min_count="1" max_count="1"/>	<!--Soulfire Dirk-->
		</group>
		<group chance="32.0">
			<item id="31326" min_count="1" max_count="1"/>	<!--Bound Soulfire Dirk - Mana Up-->
		</group>
		<group chance="32.0">
			<item id="31327" min_count="1" max_count="1"/>	<!--Bound Soulfire Dirk - Magic Hold-->
		</group>
		<group chance="32.0">
			<item id="31328" min_count="1" max_count="1"/>	<!--Bound Soulfire Dirk - Magic Silence-->
		</group>
	</restoration>
	<restoration skill_id="12682" skill_level="1" name="Check Item" consume_item_id="32073">
		<!--Item: ID[32073, NAME[Unidentified Mystic's Stockings]-->
		<group chance="4.0">
			<item id="468" min_count="1" max_count="1"/>	<!--Mystic's Stockings-->
		</group>
		<group chance="96.0">
			<item id="31329" min_count="1" max_count="1"/>	<!--Bound Mystic's Stockings-->
		</group>
	</restoration>
	<restoration skill_id="12683" skill_level="1" name="Check Item" consume_item_id="32074">
		<!--Item: ID[32074, NAME[Unidentified Mystic's Tunic]-->
		<group chance="4.0">
			<item id="435" min_count="1" max_count="1"/>	<!--Mystic's Tunic-->
		</group>
		<group chance="96.0">
			<item id="31330" min_count="1" max_count="1"/>	<!--Bound Mystic's Tunic-->
		</group>
	</restoration>
	<restoration skill_id="12684" skill_level="1" name="Check Item" consume_item_id="32075">
		<!--Item: ID[32075, NAME[Unidentified Staff of Magic]-->
		<group chance="4.0">
			<item id="186" min_count="1" max_count="1"/>	<!--Staff of Magic-->
		</group>
		<group chance="96.0">
			<item id="31331" min_count="1" max_count="1"/>	<!--Bound Staff of Magic-->
		</group>
	</restoration>
	<restoration skill_id="12685" skill_level="1" name="Check Item" consume_item_id="32076">
		<!--Item: ID[32076, NAME[Unidentified Ring of Magic]-->
		<group chance="4.0">
			<item id="879" min_count="1" max_count="1"/>	<!--Enchanted Ring-->
		</group>
		<group chance="96.0">
			<item id="31332" min_count="1" max_count="1"/>	<!--Bound Enchanted Ring-->
		</group>
	</restoration>
	<restoration skill_id="12686" skill_level="1" name="Check Item" consume_item_id="32077">
		<!--Item: ID[32077, NAME[Unidentified Ring of Magic]-->
		<group chance="4.0">
			<item id="879" min_count="1" max_count="1"/>	<!--Enchanted Ring-->
		</group>
		<group chance="96.0">
			<item id="31332" min_count="1" max_count="1"/>	<!--Bound Enchanted Ring-->
		</group>
	</restoration>
	<restoration skill_id="12687" skill_level="1" name="Check Item" consume_item_id="32078">
		<!--Item: ID[32078, NAME[Unidentified Necklace of Magic]-->
		<group chance="4.0">
			<item id="911" min_count="1" max_count="1"/>	<!--Enchanted Necklace-->
		</group>
		<group chance="96.0">
			<item id="31334" min_count="1" max_count="1"/>	<!--Bound Enchanted Necklace-->
		</group>
	</restoration>
	<restoration skill_id="12688" skill_level="1" name="Check Item" consume_item_id="32079">
		<!--Item: ID[32079, NAME[Unidentified Necklace of Magic]-->
		<group chance="4.0">
			<item id="911" min_count="1" max_count="1"/>	<!--Enchanted Necklace-->
		</group>
		<group chance="96.0">
			<item id="31334" min_count="1" max_count="1"/>	<!--Bound Enchanted Necklace-->
		</group>
	</restoration>
	<restoration skill_id="12689" skill_level="1" name="Check Item" consume_item_id="32080">
		<!--Item: ID[32080, NAME[Unidentified Earring of Magic]-->
		<group chance="4.0">
			<item id="848" min_count="1" max_count="1"/>	<!--Enchanted Earring-->
		</group>
		<group chance="96.0">
			<item id="31336" min_count="1" max_count="1"/>	<!--Bound Enchanted Earring-->
		</group>
	</restoration>
	<restoration skill_id="12690" skill_level="1" name="Check Item" consume_item_id="32081">
		<!--Item: ID[32081, NAME[Unidentified Earring of Magic]-->
		<group chance="4.0">
			<item id="848" min_count="1" max_count="1"/>	<!--Enchanted Earring-->
		</group>
		<group chance="96.0">
			<item id="31336" min_count="1" max_count="1"/>	<!--Bound Enchanted Earring-->
		</group>
	</restoration>
	<restoration skill_id="12691" skill_level="1" name="Check Item" consume_item_id="32082">
		<!--Item: ID[32082, NAME[Unidentified Staff of Mana]-->
		<group chance="4.0">
			<item id="185" min_count="1" max_count="1"/>	<!--Staff of Mana-->
		</group>
		<group chance="96.0">
			<item id="31338" min_count="1" max_count="1"/>	<!--Bound Staff of Mana-->
		</group>
	</restoration>
	<restoration skill_id="12692" skill_level="1" name="Check Item" consume_item_id="32083">
		<!--Item: ID[32083, NAME[Unidentified Dagger of Mana]-->
		<group chance="4.0">
			<item id="238" min_count="1" max_count="1"/>	<!--Dagger of Mana-->
		</group>
		<group chance="96.0">
			<item id="31339" min_count="1" max_count="1"/>	<!--Bound Dagger of Mana-->
		</group>
	</restoration>
	<restoration skill_id="12693" skill_level="1" name="Check Item" consume_item_id="32084">
		<!--Item: ID[32084, NAME[Unidentified Ring Breastplate]-->
		<group chance="4.0">
			<item id="347" min_count="1" max_count="1"/>	<!--Ring Mail Breastplate-->
		</group>
		<group chance="96.0">
			<item id="31340" min_count="1" max_count="1"/>	<!--Bound Ring Mail Breastplate-->
		</group>
	</restoration>
	<restoration skill_id="12694" skill_level="1" name="Check Item" consume_item_id="32085">
		<!--Item: ID[32085, NAME[Unidentified Long Bow]-->
		<group chance="4.0">
			<item id="275" min_count="1" max_count="1"/>	<!--Long Bow-->
		</group>
		<group chance="96.0">
			<item id="31341" min_count="1" max_count="1"/>	<!--Bound Long Bow-->
		</group>
	</restoration>
	<restoration skill_id="12695" skill_level="1" name="Check Item" consume_item_id="32086">
		<!--Item: ID[32086, NAME[Unidentified Rapier]-->
		<group chance="4.0">
			<item id="9209" min_count="1" max_count="1"/>	<!--Rapier-->
		</group>
		<group chance="96.0">
			<item id="31342" min_count="1" max_count="1"/>	<!--Bound Rapier-->
		</group>
	</restoration>
	<restoration skill_id="12696" skill_level="1" name="Check Item" consume_item_id="32087">
		<!--Item: ID[32087, NAME[Unidentified Raid Sword*Raid Sword]-->
		<group chance="4.0">
			<item id="2599" min_count="1" max_count="1"/>	<!--Raid Sword*Raid Sword-->
		</group>
		<group chance="96.0">
			<item id="31343" min_count="1" max_count="1"/>	<!--Bound Raid Sword*Raid Sword-->
		</group>
	</restoration>
	<restoration skill_id="12697" skill_level="1" name="Check Item" consume_item_id="32088">
		<!--Item: ID[32088, NAME[Unidentified Raid Sword]-->
		<group chance="4.0">
			<item id="133" min_count="1" max_count="1"/>	<!--Raid Sword-->
		</group>
		<group chance="32.0">
			<item id="31345" min_count="1" max_count="1"/>	<!--Bound Raid Sword - Focus-->
		</group>
		<group chance="32.0">
			<item id="31346" min_count="1" max_count="1"/>	<!--Bound Raid Sword - Critical Drain-->
		</group>
		<group chance="32.0">
			<item id="31347" min_count="1" max_count="1"/>	<!--Bound Raid Sword - Critical Poison-->
		</group>
	</restoration>
	<restoration skill_id="12698" skill_level="1" name="Check Item" consume_item_id="32089">
		<!--Item: ID[32089, NAME[Unidentified Red Crescent]-->
		<group chance="4.0">
			<item id="847" min_count="1" max_count="1"/>	<!--Red Crescent Earring-->
		</group>
		<group chance="96.0">
			<item id="31352" min_count="1" max_count="1"/>	<!--Bound Red Crescent-->
		</group>
	</restoration>
	<restoration skill_id="12699" skill_level="1" name="Check Item" consume_item_id="32090">
		<!--Item: ID[32090, NAME[Unidentified Leather Armor of Doom]-->
		<group chance="4.0">
			<item id="2392" min_count="1" max_count="1"/>	<!--Leather Armor of Doom-->
		</group>
		<group chance="96.0">
			<item id="31353" min_count="1" max_count="1"/>	<!--Bound Leather Armor of Doom-->
		</group>
	</restoration>
</list>
