<?xml version="1.0" encoding="UTF-8"?>
<!DOCTYPE list SYSTEM "restoration_info.dtd">
<!--By Bonux-->
<list>
	<restoration skill_id="6121" skill_level="1" name="Agathion's New Year's Gift 1">
		<group chance="100.0">
			<item id="14676" min_count="1" max_count="1"/>	<!--Agathion's New Year's Gift-->
		</group>
	</restoration>
	<restoration skill_id="6122" skill_level="1" name="Agathion's New Year's Gift 2">
		<group chance="100.0">
			<item id="14677" min_count="1" max_count="1"/>	<!--Agathion's New Year's Gift-->
		</group>
	</restoration>
</list>