<?xml version='1.0' encoding='utf-8'?>
<!--
  ~ Copyright Mazaffaka Project (c) 2013.
  -->

<list>
    <item>
        <ingredient id="13419" count="200"/>
        <production id="20659" count="1"/>
    </item>
    <item>
        <ingredient id="13419" count="200"/>
        <production id="20660" count="1"/>
    </item>
    <item>
        <ingredient id="13419" count="200"/>
        <production id="12779" count="1"/>
    </item>
    <item>
        <ingredient id="13419" count="200"/>
        <production id="12780" count="1"/>
    </item>
    <item>
        <ingredient id="13419" count="200"/>
        <production id="13545" count="1"/>
    </item>
    <item>
        <ingredient id="13419" count="200"/>
        <production id="13543" count="1"/>
    </item>
    <item>
        <ingredient id="13419" count="200"/>
        <production id="14675" count="1"/>
    </item>
    <item>
        <ingredient id="13419" count="200"/>
        <production id="20006" count="1"/>
    </item>
    <item>
        <ingredient id="13419" count="200"/>
        <production id="20007" count="1"/>
    </item>
    <item>
        <ingredient id="13419" count="200"/>
        <production id="20008" count="1"/>
    </item>
    <item>
        <ingredient id="13419" count="200"/>
        <production id="20012" count="1"/>
    </item>
    <item>
        <ingredient id="13419" count="200"/>
        <production id="20063" count="1"/>
    </item>
    <item>
        <ingredient id="13419" count="200"/>
        <production id="20064" count="1"/>
    </item>
    <item>
        <ingredient id="13419" count="200"/>
        <production id="20065" count="1"/>
    </item>
    <item>
        <ingredient id="13419" count="200"/>
        <production id="20212" count="1"/>
    </item>
    <item>
        <ingredient id="13419" count="200"/>
        <production id="20213" count="1"/>
    </item>
    <item>
        <ingredient id="13419" count="200"/>
        <production id="20221" count="1"/>
    </item>
    <item>
        <ingredient id="13419" count="200"/>
        <production id="20222" count="1"/>
    </item>
    <item>
        <ingredient id="13419" count="200"/>
        <production id="20223" count="1"/>
    </item>
    <item>
        <ingredient id="13419" count="200"/>
        <production id="20236" count="1"/>
    </item>
    <item>
        <ingredient id="13419" count="200"/>
        <production id="20245" count="1"/>
    </item>
    <item>
        <ingredient id="13419" count="200"/>
        <production id="20246" count="1"/>
    </item>
    <item>
        <ingredient id="13419" count="200"/>
        <production id="20247" count="1"/>
    </item>
    <item>
        <ingredient id="13419" count="200"/>
        <production id="20252" count="1"/>
    </item>
    <item>
        <ingredient id="13419" count="200"/>
        <production id="20253" count="1"/>
    </item>
    <item>
        <ingredient id="13419" count="200"/>
        <production id="20297" count="1"/>
    </item>
    <item>
        <ingredient id="13419" count="200"/>
        <production id="20299" count="1"/>
    </item>
    <item>
        <ingredient id="13419" count="200"/>
        <production id="20301" count="1"/>
    </item>
    <item>
        <ingredient id="13419" count="200"/>
        <production id="20303" count="1"/>
    </item>
    <item>
        <ingredient id="13419" count="200"/>
        <production id="20307" count="1"/>
    </item>
    <item>
        <ingredient id="13419" count="200"/>
        <production id="20309" count="1"/>
    </item>
    <item>
        <ingredient id="13419" count="200"/>
        <production id="20320" count="1"/>
    </item>
    <item>
        <ingredient id="13419" count="200"/>
        <production id="20312" count="1"/>
    </item>
    <item>
        <ingredient id="13419" count="200"/>
        <production id="20591" count="1"/>
    </item>
    <item>
        <ingredient id="13419" count="200"/>
        <production id="20654" count="1"/>
    </item>
    <item>
        <ingredient id="13419" count="200"/>
        <production id="20656" count="1"/>
    </item>
    <item>
        <ingredient id="13419" count="200"/>
        <production id="20658" count="1"/>
    </item>
    <item>
        <ingredient id="13419" count="200"/>
        <production id="20660" count="1"/>
    </item>
    <item>
        <ingredient id="13419" count="200"/>
        <production id="20662" count="1"/>
    </item>
    <item>
        <ingredient id="13419" count="200"/>
        <production id="20664" count="1"/>
    </item>
    <item>
        <ingredient id="13419" count="200"/>
        <production id="20726" count="1"/>
    </item>
    <item>
        <ingredient id="13419" count="200"/>
        <production id="20732" count="1"/>
    </item>
    <item>
        <ingredient id="13419" count="200"/>
        <production id="20733" count="1"/>
    </item>
    <item>
        <ingredient id="13419" count="200"/>
        <production id="20779" count="1"/>
    </item>
    <item>
        <ingredient id="13419" count="200"/>
        <production id="20782" count="1"/>
    </item>
    <item>
        <ingredient id="13419" count="200"/>
        <production id="20783" count="1"/>
    </item>
    <item>
        <ingredient id="13419" count="200"/>
        <production id="20784" count="1"/>
    </item>
    <item>
        <ingredient id="13419" count="200"/>
        <production id="21986" count="1"/>
    </item>
    <item>
        <ingredient id="4357" count="20"/>
        <ingredient id="13419" count="200"/>
        <production id="22047" count="1"/>
    </item>
    <item>
        <ingredient id="4357" count="20"/>
        <ingredient id="13419" count="200"/>
        <production id="22048" count="1"/>
    </item>
    <item>
        <ingredient id="4357" count="20"/>
        <ingredient id="13419" count="200"/>
        <production id="22050" count="1"/>
    </item>
    <item>
        <ingredient id="4357" count="20"/>
        <ingredient id="13419" count="200"/>
        <production id="22052" count="1"/>
    </item>
    <item>
        <ingredient id="4357" count="20"/>
        <ingredient id="13419" count="200"/>
        <production id="22054" count="1"/>
    </item>
    <item>
        <ingredient id="4357" count="20"/>
        <ingredient id="13419" count="200"/>
        <production id="22056" count="1"/>
    </item>
    <item>
        <ingredient id="4357" count="20"/>
        <ingredient id="13419" count="200"/>
        <production id="22058" count="1"/>
    </item>
    <item>
        <ingredient id="4357" count="20"/>
        <ingredient id="13419" count="200"/>
        <production id="22060" count="1"/>
    </item>
    <item>
        <ingredient id="4357" count="20"/>
        <ingredient id="13419" count="200"/>
        <production id="20970" count="1"/>
    </item>
    <item>
        <ingredient id="4357" count="30"/>
        <ingredient id="13419" count="500"/>
        <production id="21165" count="1"/>
    </item>
    <item>
        <ingredient id="4357" count="40"/>
        <ingredient id="13419" count="700"/>
        <production id="22062" count="1"/>
    </item>
</list>